README.md
license.txt
setup.py
pro_video_mj_teste.egg-info/PKG-INFO
pro_video_mj_teste.egg-info/SOURCES.txt
pro_video_mj_teste.egg-info/dependency_links.txt
pro_video_mj_teste.egg-info/top_level.txt
pro_video_tools/__init__.py
pro_video_tools/camera.py
pro_video_tools/video.py