Metadata-Version: 2.1
Name: pro-video-mj-teste
Version: 1.0
Summary: Este pacote irá fornecer ferramentas de processamentos de multimidia
Home-page: UNKNOWN
Author: Mauro Júnior
Author-email: email@email.com
License: UNKNOWN
Keywords: camera,video,processamento
Platform: UNKNOWN
License-File: license.txt
